ukkonen_rs-0.1.0.post1.dist-info/METADATA
ukkonen_rs-0.1.0.post1.dist-info/WHEEL
ukkonen_rs/__init__.py
ukkonen_rs/ukkonen_rs.abi3.so
ukkonen_rs-0.1.0.post1.dist-info/RECORD
