Metadata-Version: 2.1
Name: ukkonen_rs
Version: 0.1.0.post1
Classifier: Programming Language :: Python
Classifier: Programming Language :: Rust
Classifier: Programming Language :: Python :: 3.7
Classifier: Programming Language :: Python :: 3.8
Classifier: Programming Language :: Python :: 3.9
Classifier: Programming Language :: Python :: 3.10
Classifier: Development Status :: 4 - Beta
Classifier: Intended Audience :: Developers
Classifier: License :: OSI Approved :: MIT License
Classifier: Operating System :: Microsoft :: Windows
Classifier: Operating System :: POSIX :: Linux
Classifier: Operating System :: MacOS
Summary: Fast approximate edit distance.
Keywords: levenshtein,editdistance
Author-email: Ethan Smith <ethan@ethanhs.me>
License: Copyright (c) 2021 Ethan Smith
Requires-Python: >=3.6
Project-URL: Source, https://github.com/ethanhs/ukkonen
